container
lastree
original
output
