Metadata-Version: 2.1
Name: lastree
Version: 9.5.2024
Summary: A tool box to use for process sfm point cloud of the tree and get the tree structure
Author-email: Jiawei Li <Jiaweiliwork@outlook.com>
License:                     GNU GENERAL PUBLIC LICENSE
Project-URL: Homepage, https://github.com/jldz9/point_cloud_tree_detection_ex
Project-URL: Issues, https://github.com/jldz9/point_cloud_tree_detection_ex/issues
Classifier: Programming Language :: Python :: 3
Classifier: License :: OSI Approved :: GNU General Public License v3 (GPLv3)
Classifier: Operating System :: OS Independent
License-File: LICENSE
Requires-Dist: numpy
Requires-Dist: pandas
